snowfl/__init__.py
snowfl/main.py
snowfl/snowfl.py
snowfl/lib/__init__.py
snowfl/lib/errors.py
snowfl/lib/get_api_key.py
snowfl-0.4.0.dist-info/licenses/LICENSE
snowfl-0.4.0.dist-info/METADATA
snowfl-0.4.0.dist-info/WHEEL
snowfl-0.4.0.dist-info/top_level.txt
snowfl-0.4.0.dist-info/RECORD
