Metadata-Version: 2.4
Name: snowfl
Version: 0.4.0
Summary: An unofficial Python wrapper for the Snowfl API, enabling programmatic torrent searches.
Requires-Python: >=3.14
License-File: LICENSE
Requires-Dist: certifi
Requires-Dist: charset-normalizer
Requires-Dist: idna
Requires-Dist: requests
Requires-Dist: urllib3
Provides-Extra: dev
Requires-Dist: pytest; extra == "dev"
Requires-Dist: coverage; extra == "dev"
Requires-Dist: build; extra == "dev"
Requires-Dist: twine; extra == "dev"
Dynamic: license-file
